logngraph/__init__.py
logngraph/errors.py
logngraph/vector.py
logngraph/graph/__init__.py
logngraph/graph/graph.py
logngraph/log/__init__.py
logngraph/log/levels.py
logngraph/log/log.py
logngraph-0.0.19.dist-info/licenses/LICENSE
logngraph-0.0.19.dist-info/METADATA
logngraph-0.0.19.dist-info/WHEEL
logngraph-0.0.19.dist-info/top_level.txt
logngraph-0.0.19.dist-info/RECORD
