Metadata-Version: 2.4
Name: logngraph
Version: 0.0.19
Summary: Draw primitives and save your logs!
Author-email: Vadim Gladushev <vadim.gladushev@mail.ru>
License-Expression: MIT
Project-URL: Documetation, https://logngraph.readthedocs.io/en/latest
Project-URL: Repository, https://github.com/GS11566/logngraph.git
Project-URL: Issues, https://github.com/GS11566/logngraph/issues
Keywords: log,logging,graphics,primitives,pygame
Classifier: Programming Language :: Python :: 3
Classifier: Operating System :: OS Independent
Classifier: Development Status :: 2 - Pre-Alpha
Classifier: Intended Audience :: Education
Classifier: Intended Audience :: Developers
Classifier: Programming Language :: Python :: 3.12
Classifier: Programming Language :: Python :: 3.13
Requires-Python: >=3.12
License-File: LICENSE
Requires-Dist: pygame
Dynamic: license-file
